{
    "MetaModulePluginMaintainer": "4ms Company",
    "MetaModulePluginMaintainerEmail": "4ms@4mscompany.com",
    "MetaModulePluginMaintainerUrl": "",
    "MetaModuleDescription": "",
    "MetaModuleIncludedModules": [
	{
		"slug": "Fence",
		"name": "Fence"
	},
	{
		"slug": "Swing",
		"name": "Swing"
	},
	{
		"slug": "Mother",
		"name": "Mother"
	},
	{
		"slug": "Phrase",
		"name": "Phrase"
	},
	{
		"slug": "Dejavu",
		"name": "Dejavu"
	},
	{
		"slug": "Gator",
		"name": "Gator"
	},
	{
		"slug": "Resc",
		"name": "Resc"
	},
	{
		"slug": "Morph",
		"name": "Morph"
	},
	{
		"slug": "Morpheus",
		"name": "Morpheus"
	}
    ]
}
